ReaderBOTDA/__init__.py
ReaderBOTDA/converter.py
ReaderBOTDA/plotter/__init__.py
ReaderBOTDA/plotter/abc.py
ReaderBOTDA/plotter/bokeh.py
ReaderBOTDA/plotter/plotly.py
ReaderBOTDA/reader.py
ReaderBOTDA/script.py
ReaderBOTDA/settings.py
readerbotda-1.4.2.dist-info/entry_points.txt
readerbotda-1.4.2.dist-info/METADATA
readerbotda-1.4.2.dist-info/WHEEL
readerbotda-1.4.2.dist-info/RECORD
