Metadata-Version: 2.3
Name: readerbotda
Version: 1.4.2
Summary: Pacchetto per lettura e visualizzazione file di log sensore BOTDA Cohaerentia
Author: Marco Brunero
Author-email: marco.brunero@cohaerentia.com
Requires-Python: >3.10
Classifier: Programming Language :: Python :: 3
Classifier: Programming Language :: Python :: 3.11
Classifier: Programming Language :: Python :: 3.12
Classifier: Programming Language :: Python :: 3.13
Requires-Dist: bokeh (>=3.7.2,<4.0.0)
Requires-Dist: dacite (>=1.9.2,<2.0.0)
Requires-Dist: h5py (>=3.14.0,<4.0.0)
Requires-Dist: nbformat (>=5.10.4,<6.0.0)
Requires-Dist: numpy (>=2.2.4,<3.0.0)
Requires-Dist: plotly (>=6.0.1,<7.0.0)
Requires-Dist: progress (>=1.6,<2.0)
Requires-Dist: typer (>=0.15.2,<0.16.0)
